DatastreamDSWS/DS_Requests.py
DatastreamDSWS/DS_Response.py
DatastreamDSWS/__init__.py
DatastreamDSWS-1.0.10.dist-info/METADATA
DatastreamDSWS-1.0.10.dist-info/RECORD
DatastreamDSWS-1.0.10.dist-info/WHEEL
DatastreamDSWS-1.0.10.dist-info/top_level.txt
